{
  "resourceType": "Condition",
  "id": "con-pat014-obesity",
  "clinicalStatus": {
    "coding": [
      {
        "code": "active",
        "system": "http://terminology.hl7.org/CodeSystem/condition-clinical"
      }
    ]
  },
  "verificationStatus": {
    "coding": [
      {
        "code": "confirmed",
        "system": "http://terminology.hl7.org/CodeSystem/condition-ver-status"
      }
    ]
  },
  "category": [
    {
      "coding": [
        {
          "system": "http://terminology.hl7.org/CodeSystem/condition-category",
          "code": "encounter-diagnosis",
          "display": "Encounter Diagnosis"
        }
      ]
    }
  ],
  "code": {
    "coding": [
      {
        "system": "http://snomed.info/sct",
        "code": "83911000119104",
        "display": "Severe obesity (disorder)"
      }
    ]
  },
  "subject": {
    "reference": "Patient/pat014"
  }
}